pybit/__init__.py
pybit/_http_manager.py
pybit/_websocket_stream.py
pybit/account_asset.py
pybit/exceptions.py
pybit/inverse_futures.py
pybit/inverse_perpetual.py
pybit/spot.py
pybit/test.py
pybit/usdc_options.py
pybit/usdc_perpetual.py
pybit/usdt_perpetual.py
pybitcs-2.2.2rc2.dist-info/LICENSE
pybitcs-2.2.2rc2.dist-info/METADATA
pybitcs-2.2.2rc2.dist-info/WHEEL
pybitcs-2.2.2rc2.dist-info/top_level.txt
pybitcs-2.2.2rc2.dist-info/RECORD
