Metadata-Version: 2.1
Name: pybitcs
Version: 2.2.2rc2
Summary: Python3 Bybit HTTP/WebSocket API Connector
Home-page: https://github.com/CryptoSenseiZA/pybit
Author: Dexter Dickinson
Author-email: dexter.dickinson@bybit.com
License: MIT License
Keywords: bybit api connector
Classifier: Development Status :: 4 - Beta
Classifier: Intended Audience :: Developers
Classifier: Topic :: Software Development :: Libraries :: Python Modules
Classifier: License :: OSI Approved :: MIT License
Classifier: Programming Language :: Python :: 3.6
Classifier: Programming Language :: Python :: 3.7
Classifier: Programming Language :: Python :: 3.8
Classifier: Programming Language :: Python :: 3.9
Requires-Python: >=3.6
License-File: LICENSE
Requires-Dist: requests
Requires-Dist: websocket-client
Requires-Dist: websockets
